{
    "coord": {
        "lon": 30.2642,
        "lat": 59.8944
    },
    "weather": [
        {
            "id": 803,
            "main": "Clouds",
            "description": "облачно с прояснениями",
            "icon": "04d"
        }
    ],
    "base": "stations",
    "main": {
        "temp": 5.03,
        "feels_like": 5.03,
        "temp_min": 4.08,
        "temp_max": 5.03,
        "pressure": 1015,
        "humidity": 89,
        "sea_level": 1015,
        "grnd_level": 1014
    },
    "visibility": 10000,
    "wind": {
        "speed": 0,
        "deg": 0
    },
    "clouds": {
        "all": 75
    },
    "dt": 1761031416,
    "sys": {
        "type": 2,
        "id": 2045711,
        "country": "RU",
        "sunrise": 1761022355,
        "sunset": 1761057254
    },
    "timezone": 10800,
    "id": 498817,
    "name": "Санкт-Петербург",
    "cod": 200,
    "city": "Saint Petersburg",
    "timestamp": "2025-10-21T07:23:36.252876",
    "source": "openweathermap.org"
}