{
    "coord": {
        "lon": 30.2642,
        "lat": 59.8944
    },
    "weather": [
        {
            "id": 300,
            "main": "Drizzle",
            "description": "небольшая морось",
            "icon": "09n"
        },
        {
            "id": 701,
            "main": "Mist",
            "description": "туман",
            "icon": "50n"
        }
    ],
    "base": "stations",
    "main": {
        "temp": 10.03,
        "feels_like": 9.54,
        "temp_min": 10.03,
        "temp_max": 10.08,
        "pressure": 995,
        "humidity": 94,
        "sea_level": 995,
        "grnd_level": 995
    },
    "visibility": 4900,
    "wind": {
        "speed": 5,
        "deg": 120
    },
    "clouds": {
        "all": 100
    },
    "dt": 1761405467,
    "sys": {
        "type": 2,
        "id": 2045711,
        "country": "RU",
        "sunrise": 1761368559,
        "sunset": 1761402187
    },
    "timezone": 10800,
    "id": 498817,
    "name": "Санкт-Петербург",
    "cod": 200,
    "city": "Saint Petersburg",
    "timestamp": "2025-10-25T15:20:42.171441",
    "source": "openweathermap.org"
}