{
    "coord": {
        "lon": 30.2642,
        "lat": 59.8944
    },
    "weather": [
        {
            "id": 800,
            "main": "Clear",
            "description": "ясно",
            "icon": "01n"
        }
    ],
    "base": "stations",
    "main": {
        "temp": 3.36,
        "feels_like": 0.54,
        "temp_min": 1.08,
        "temp_max": 3.36,
        "pressure": 1016,
        "humidity": 81,
        "sea_level": 1016,
        "grnd_level": 1016
    },
    "visibility": 10000,
    "wind": {
        "speed": 3,
        "deg": 190
    },
    "clouds": {
        "all": 0
    },
    "dt": 1760908757,
    "sys": {
        "type": 2,
        "id": 2045711,
        "country": "RU",
        "sunrise": 1760935806,
        "sunset": 1760971023
    },
    "timezone": 10800,
    "id": 498817,
    "name": "Санкт-Петербург",
    "cod": 200,
    "city": "Saint Petersburg",
    "timestamp": "2025-10-19T21:19:17.081079",
    "source": "openweathermap.org"
}