{
    "coord": {
        "lon": 49.1221,
        "lat": 55.7887
    },
    "weather": [
        {
            "id": 803,
            "main": "Clouds",
            "description": "облачно с прояснениями",
            "icon": "04n"
        }
    ],
    "base": "stations",
    "main": {
        "temp": 6.34,
        "feels_like": 4.72,
        "temp_min": 6.34,
        "temp_max": 6.34,
        "pressure": 1017,
        "humidity": 69,
        "sea_level": 1017,
        "grnd_level": 1003
    },
    "visibility": 10000,
    "wind": {
        "speed": 2.22,
        "deg": 220,
        "gust": 3.96
    },
    "clouds": {
        "all": 80
    },
    "dt": 1760460788,
    "sys": {
        "type": 1,
        "id": 9038,
        "country": "RU",
        "sunrise": 1760411517,
        "sunset": 1760449606
    },
    "timezone": 10800,
    "id": 551487,
    "name": "Казань",
    "cod": 200,
    "city": "Kazan",
    "timestamp": "2025-10-14T16:53:07.759239",
    "source": "openweathermap.org"
}